{
  "configVersion": 1,
  "index": "/index.html",
  "assetGroups": [
    {
      "name": "app",
      "installMode": "prefetch",
      "updateMode": "prefetch",
      "urls": [
        "/favicon.ico",
        "/index.html",
        "/inline.e5f3ae9e37bed053334f.bundle.js",
        "/main.8dd9da3aaa372e716778.bundle.js",
        "/polyfills.486a8dcfb7a22be09ea9.bundle.js",
        "/styles.28b1def8dff2d136c339.bundle.css"
      ],
      "patterns": []
    },
    {
      "name": "assets",
      "installMode": "lazy",
      "updateMode": "prefetch",
      "urls": [],
      "patterns": []
    }
  ],
  "dataGroups": [],
  "hashTable": {
    "/inline.e5f3ae9e37bed053334f.bundle.js": "6d04bb7d830e5273bed5665f9c49d19be17a9290",
    "/main.8dd9da3aaa372e716778.bundle.js": "dd827c3291c93e53b21d45594b7433d6bb3e0497",
    "/polyfills.486a8dcfb7a22be09ea9.bundle.js": "9d6e3abd3d17d64718f78af0dcb54e2f893915a0",
    "/styles.28b1def8dff2d136c339.bundle.css": "3ae264f5f408cb469cac81843714d45ced36ca1d",
    "/favicon.ico": "84161b857f5c547e3699ddfbffc6d8d737542e01",
    "/index.html": "6781c5106136f6327f9cd6b99dd2dbae74ba2f31"
  }
}